{"links":{"next":null,"previous":null},"count":27,"total_pages":1,"results":[{"id":19498,"provider_id":"30724","name":"Mewar Hospital Pvt. Ltd.","address":"Priyadarshani Nagar Bedla","city":"Udaipur","state":"Rajasthan","postal_code":313011,"logo":"https://rules.nivabupa.com/media/default_hospital.svg","latitude":24.62937,"longitude":73.69612,"beds_count":"50","email_id":"cashless@mewarhospitals.com","website":"http://www.mewarhospitals.com/","ppn_available":false,"doctors_count":"18","rating":0,"avg_rating":0,"review_count":"NA","rating_count":"NA","reviews":"120","accreditions":"NABH Entry Level","treatment_cost":"NA","customer_expense":"NA","stay_duration":"2","primary_phone":"0294-2442006","additional_phone":"7230050586","last_updated_at":"2021-07-20 00:00:00","ppn_benefits":{"ppn_spoc_phone_no":null,"nbhi_non_payable_waiver":null,"discount_on_opd_consultation":null,"discount_on_opd_investigation":null,"discount_on_health_check_up":null,"free_ambulance":null,"ppn_spoc_name":null},"poc":null,"ir":null},{"id":18421,"provider_id":"20923","name":"GBH American Hospital","address":"101 Kothi Bagh Bhatt Ji Ki Bahri","city":"Udaipur","state":"Rajasthan","postal_code":313001,"logo":"https://rules.nivabupa.com/media/default_hospital.svg","latitude":24.593547,"longitude":73.696278,"beds_count":"150","email_id":"insurance@gbhamericanhospital.com","website":"http://www.gbhamericanhospital.com/","ppn_available":false,"doctors_count":"35","rating":0,"avg_rating":0,"review_count":2,"rating_count":2,"reviews":"120","accreditions":"NABH Higher Level","treatment_cost":"NA","customer_expense":"NA","stay_duration":"5","primary_phone":"0294-3056000","additional_phone":"9314402333","last_updated_at":"2021-04-22 00:00:00","ppn_benefits":{"ppn_spoc_phone_no":null,"nbhi_non_payable_waiver":null,"discount_on_opd_consultation":null,"discount_on_opd_investigation":null,"discount_on_health_check_up":null,"free_ambulance":null,"ppn_spoc_name":null},"poc":null,"ir":null},{"id":19865,"provider_id":"32472","name":"Shantiraj Hospital Pvt Ltd.","address":"699, Arjun Nagar, Hiran Magri, Sector 11","city":"Udaipur","state":"Rajasthan","postal_code":313001,"logo":"https://rules.nivabupa.com/media/default_hospital.svg","latitude":24.571641,"longitude":73.691659,"beds_count":"30","email_id":"balu.kheroda@gmail.com","website":"http://www.shantirajhospital.comq/","ppn_available":false,"doctors_count":"13","rating":0,"avg_rating":0,"review_count":"NA","rating_count":"NA","reviews":"120","accreditions":"NA","treatment_cost":"NA","customer_expense":"NA","stay_duration":"NA","primary_phone":"0294-2481084","additional_phone":"9799119446","last_updated_at":"2021-03-31 00:00:00","ppn_benefits":{"ppn_spoc_phone_no":null,"nbhi_non_payable_waiver":null,"discount_on_opd_consultation":null,"discount_on_opd_investigation":null,"discount_on_health_check_up":null,"free_ambulance":null,"ppn_spoc_name":null},"poc":null,"ir":null},{"id":20105,"provider_id":"33081","name":"Jai Drishti Eye Hospital","address":"78, Tagore Nagar, Sector - 4, Hiran Nagri","city":"Udaipur","state":"Rajasthan","postal_code":313004,"logo":"https://rules.nivabupa.com/media/default_hospital.svg","latitude":24.57127,"longitude":73.691544,"beds_count":"15","email_id":"dr.upavan@gmail.com","website":"http://www.jaidrishti.com/","ppn_available":false,"doctors_count":"8","rating":0,"avg_rating":0,"review_count":"NA","rating_count":"NA","reviews":"120","accreditions":"NA","treatment_cost":"NA","customer_expense":"NA","stay_duration":"NA","primary_phone":"0294-2464178","additional_phone":"7737666603","last_updated_at":"2021-03-31 00:00:00","ppn_benefits":{"ppn_spoc_phone_no":null,"nbhi_non_payable_waiver":null,"discount_on_opd_consultation":null,"discount_on_opd_investigation":null,"discount_on_health_check_up":null,"free_ambulance":null,"ppn_spoc_name":null},"poc":null,"ir":null},{"id":19605,"provider_id":"31170","name":"ASG Hospital Pvt. Ltd. Udaipur","address":"7C-2 Meera Marg Near Mirabai Girls College, Madhuban","city":"Udaipur","state":"Rajasthan","postal_code":313001,"logo":"https://rules.nivabupa.com/media/default_hospital.svg","latitude":24.5956,"longitude":73.6931,"beds_count":"10","email_id":"hr@asgeyehospital.com","website":"https://www.asgeyehospital.com/","ppn_available":false,"doctors_count":"6","rating":0,"avg_rating":0,"review_count":"NA","rating_count":"NA","reviews":"120","accreditions":"NA","treatment_cost":"NA","customer_expense":"NA","stay_duration":"2","primary_phone":"0291-2638824","additional_phone":"8875020425","last_updated_at":"2021-06-03 00:00:00","ppn_benefits":{"ppn_spoc_phone_no":null,"nbhi_non_payable_waiver":null,"discount_on_opd_consultation":null,"discount_on_opd_investigation":null,"discount_on_health_check_up":null,"free_ambulance":null,"ppn_spoc_name":null},"poc":null,"ir":null},{"id":21718,"provider_id":"57187","name":"Dr. Chaudhary Hospital and Medical Research Centre Pvt. Ltd.","address":"473, Sector-4 Hiran Magri, Udaipur","city":"Udaipur","state":"Rajasthan","postal_code":313002,"logo":"https://rules.nivabupa.com/media/default_hospital.svg","latitude":24.56636,"longitude":73.72162,"beds_count":"150","email_id":"info@chaudharyhospital.in","website":null,"ppn_available":false,"doctors_count":"20","rating":0,"avg_rating":0,"review_count":2,"rating_count":2,"reviews":"120","accreditions":"NABH Entry Level","treatment_cost":"NA","customer_expense":"NA","stay_duration":"10","primary_phone":"9950777467","additional_phone":"9950777467","last_updated_at":"2021-03-12 00:00:00","ppn_benefits":{"ppn_spoc_phone_no":null,"nbhi_non_payable_waiver":null,"discount_on_opd_consultation":null,"discount_on_opd_investigation":null,"discount_on_health_check_up":null,"free_ambulance":null,"ppn_spoc_name":null},"poc":null,"ir":null},{"id":21792,"provider_id":"58087","name":"Pacific Institute of Medical Sciences","address":"Ambua Road, Umarda","city":"Udaipur","state":"Rajasthan","postal_code":313015,"logo":"https://rules.nivabupa.com/media/default_hospital.svg","latitude":24.50603,"longitude":73.76457,"beds_count":"738","email_id":"tpa@pacificmedicalsciences.ac.in","website":"http://www.pacificmedicalsciences.ac.in/","ppn_available":false,"doctors_count":"105","rating":0,"avg_rating":0,"review_count":"NA","rating_count":"NA","reviews":"120","accreditions":"NABH Entry Level","treatment_cost":"NA","customer_expense":"NA","stay_duration":"5","primary_phone":"9829774182","additional_phone":"9829774182","last_updated_at":"2021-03-31 00:00:00","ppn_benefits":{"ppn_spoc_phone_no":null,"nbhi_non_payable_waiver":null,"discount_on_opd_consultation":null,"discount_on_opd_investigation":null,"discount_on_health_check_up":null,"free_ambulance":null,"ppn_spoc_name":null},"poc":null,"ir":null},{"id":24367,"provider_id":"70791","name":"Shreeji Multispeciality Hospital","address":"285 Bhupalpura Main Road","city":"Udaipur","state":"Rajasthan","postal_code":313001,"logo":"https://rules.nivabupa.com/media/default_hospital.svg","latitude":24.59541,"longitude":73.69681,"beds_count":"30","email_id":"arun.shreejihospital@gmail.com","website":null,"ppn_available":false,"doctors_count":"13","rating":0,"avg_rating":0,"review_count":"NA","rating_count":"NA","reviews":"120","accreditions":"NA","treatment_cost":"NA","customer_expense":"NA","stay_duration":"NA","primary_phone":"9460825636","additional_phone":"9414120608","last_updated_at":"2021-03-25 00:00:00","ppn_benefits":{"ppn_spoc_phone_no":null,"nbhi_non_payable_waiver":null,"discount_on_opd_consultation":null,"discount_on_opd_investigation":null,"discount_on_health_check_up":null,"free_ambulance":null,"ppn_spoc_name":null},"poc":null,"ir":null},{"id":22364,"provider_id":"61983","name":"Paras Jk Hospital","address":"Plot No. 1, Near Shobhagpura Circle","city":"Udaipur","state":"Rajasthan","postal_code":313001,"logo":"https://rules.nivabupa.com/media/default_hospital.svg","latitude":24.6066,"longitude":73.71083,"beds_count":"194","email_id":"mani.bhatnagar@parshospitals.com","website":null,"ppn_available":false,"doctors_count":"68","rating":0,"avg_rating":0,"review_count":2,"rating_count":2,"reviews":"120","accreditions":"NABH Higher Level","treatment_cost":"<5,000","customer_expense":"NA","stay_duration":"8","primary_phone":"9414160182","additional_phone":"7665122737","last_updated_at":"2021-03-31 00:00:00","ppn_benefits":{"ppn_spoc_phone_no":null,"nbhi_non_payable_waiver":null,"discount_on_opd_consultation":null,"discount_on_opd_investigation":null,"discount_on_health_check_up":null,"free_ambulance":null,"ppn_spoc_name":null},"poc":null,"ir":null},{"id":23378,"provider_id":"66375","name":"GBH General Hospital and Gbh Memorial Cancer Hospital","address":"Near Transport Nagar Airport Road Bedwas","city":"Udaipur","state":"Rajasthan","postal_code":313002,"logo":"https://rules.nivabupa.com/media/default_hospital.svg","latitude":24.59172,"longitude":73.77554,"beds_count":"300","email_id":"insurance@gbhmch.org","website":null,"ppn_available":false,"doctors_count":"62","rating":0,"avg_rating":0,"review_count":"NA","rating_count":"NA","reviews":"120","accreditions":"NA","treatment_cost":"NA","customer_expense":"NA","stay_duration":"6","primary_phone":"9314402333","additional_phone":"8890616449","last_updated_at":"2021-01-18 00:00:00","ppn_benefits":{"ppn_spoc_phone_no":null,"nbhi_non_payable_waiver":null,"discount_on_opd_consultation":null,"discount_on_opd_investigation":null,"discount_on_health_check_up":null,"free_ambulance":null,"ppn_spoc_name":null},"poc":null,"ir":null},{"id":23916,"provider_id":"68527","name":"Siddhi Vinayak Hospital","address":"Ba-365 Shiv Colony Hiran Magri Sector 6","city":"Udaipur","state":"Rajasthan","postal_code":313001,"logo":"https://rules.nivabupa.com/media/default_hospital.svg","latitude":24.5574,"longitude":73.71581,"beds_count":"50","email_id":"drgjoshi@gmail.com","website":null,"ppn_available":false,"doctors_count":"21","rating":0,"avg_rating":0,"review_count":"NA","rating_count":"NA","reviews":"120","accreditions":"NA","treatment_cost":"NA","customer_expense":"NA","stay_duration":"4","primary_phone":"7877016677","additional_phone":"8107703397","last_updated_at":"2021-01-25 00:00:00","ppn_benefits":{"ppn_spoc_phone_no":null,"nbhi_non_payable_waiver":null,"discount_on_opd_consultation":null,"discount_on_opd_investigation":null,"discount_on_health_check_up":null,"free_ambulance":null,"ppn_spoc_name":null},"poc":null,"ir":null},{"id":23929,"provider_id":"68556","name":"Dr Kotharis Eye Hospital","address":"1-D Machla Magra Scheme Patel Circle","city":"Udaipur","state":"Rajasthan","postal_code":313001,"logo":"https://rules.nivabupa.com/media/default_hospital.svg","latitude":24.56568,"longitude":73.69371,"beds_count":"25","email_id":"dranilkothari@hotmail.com","website":null,"ppn_available":false,"doctors_count":"10","rating":0,"avg_rating":0,"review_count":1,"rating_count":1,"reviews":"120","accreditions":"NABH Entry Level","treatment_cost":"NA","customer_expense":"NA","stay_duration":"2","primary_phone":"9414156738","additional_phone":"8560023382","last_updated_at":"2021-02-22 00:00:00","ppn_benefits":{"ppn_spoc_phone_no":null,"nbhi_non_payable_waiver":null,"discount_on_opd_consultation":null,"discount_on_opd_investigation":null,"discount_on_health_check_up":null,"free_ambulance":null,"ppn_spoc_name":null},"poc":null,"ir":null},{"id":24110,"provider_id":"69647","name":"Bilasi Devi Gattani Hospital","address":"462-A Bhupalpura, Near Shashtri Circle","city":"Udaipur","state":"Rajasthan","postal_code":313001,"logo":"https://rules.nivabupa.com/media/default_hospital.svg","latitude":24.58857,"longitude":73.70106,"beds_count":"25","email_id":"gattanihospital@gmail.com","website":null,"ppn_available":false,"doctors_count":"11","rating":0,"avg_rating":0,"review_count":"NA","rating_count":"NA","reviews":"120","accreditions":"NA","treatment_cost":"NA","customer_expense":"NA","stay_duration":"0","primary_phone":"9414169339","additional_phone":"9414169339","last_updated_at":"2021-02-26 00:00:00","ppn_benefits":{"ppn_spoc_phone_no":null,"nbhi_non_payable_waiver":null,"discount_on_opd_consultation":null,"discount_on_opd_investigation":null,"discount_on_health_check_up":null,"free_ambulance":null,"ppn_spoc_name":null},"poc":null,"ir":null},{"id":24137,"provider_id":"69724","name":"Dr. Atray Eye Hospital","address":"19-20 First Floor Town Hall Link Road, Near Union Corporation Bank","city":"Udaipur","state":"Rajasthan","postal_code":313001,"logo":"https://rules.nivabupa.com/media/default_hospital.svg","latitude":24.58376,"longitude":73.69847,"beds_count":"10","email_id":"jpatraya@yahoo.com","website":null,"ppn_available":false,"doctors_count":"2","rating":0,"avg_rating":0,"review_count":"NA","rating_count":"NA","reviews":"120","accreditions":"NA","treatment_cost":"NA","customer_expense":"NA","stay_duration":"NA","primary_phone":"9829041330","additional_phone":"9829041330","last_updated_at":"2021-03-02 00:00:00","ppn_benefits":{"ppn_spoc_phone_no":null,"nbhi_non_payable_waiver":null,"discount_on_opd_consultation":null,"discount_on_opd_investigation":null,"discount_on_health_check_up":null,"free_ambulance":null,"ppn_spoc_name":null},"poc":null,"ir":null},{"id":24395,"provider_id":"70832","name":"Kidney Care Hospital and Research Center","address":"Near Mangalam Residency Fathepura, New Navratan Complex","city":"Udaipur","state":"Rajasthan","postal_code":313001,"logo":"https://rules.nivabupa.com/media/default_hospital.svg","latitude":24.62497,"longitude":73.69943,"beds_count":"40","email_id":"insurance.kidneycarehospital@gmail.com","website":null,"ppn_available":false,"doctors_count":"17","rating":0,"avg_rating":0,"review_count":"NA","rating_count":"NA","reviews":"120","accreditions":"NABH Entry Level","treatment_cost":"NA","customer_expense":"NA","stay_duration":"NA","primary_phone":"8233812340","additional_phone":"9799119446","last_updated_at":"2021-03-23 00:00:00","ppn_benefits":{"ppn_spoc_phone_no":null,"nbhi_non_payable_waiver":null,"discount_on_opd_consultation":null,"discount_on_opd_investigation":null,"discount_on_health_check_up":null,"free_ambulance":null,"ppn_spoc_name":null},"poc":null,"ir":null},{"id":26123,"provider_id":"86522","name":"Sudha Orthopaedic and Gynec Hospital","address":"8-9 Vrindawan Dham Road Number 1 Cps School Road New Bhopalpura","city":"Udaipur","state":"Rajasthan","postal_code":313001,"logo":"https://rules.nivabupa.com/media/default_hospital.svg","latitude":null,"longitude":null,"beds_count":"22","email_id":"sudhatpa2@gmail.com","website":"http://www.sudhahospital.in/","ppn_available":false,"doctors_count":"2","rating":0,"avg_rating":0,"review_count":"NA","rating_count":"NA","reviews":"120","accreditions":"NABH Entry Level","treatment_cost":"NA","customer_expense":"NA","stay_duration":"NA","primary_phone":"0294-2422000","additional_phone":"6375570736","last_updated_at":"2022-02-24 00:00:00","ppn_benefits":{"ppn_spoc_phone_no":null,"nbhi_non_payable_waiver":null,"discount_on_opd_consultation":null,"discount_on_opd_investigation":null,"discount_on_health_check_up":null,"free_ambulance":null,"ppn_spoc_name":null},"poc":null,"ir":null},{"id":26174,"provider_id":"86708","name":"Jivanta Children's Hospital","address":"Riddhi Siddhi Complex Panchsheel Market Hiran Magri Sector-5","city":"Udaipur","state":"Rajasthan","postal_code":313002,"logo":"https://rules.nivabupa.com/media/default_hospital.svg","latitude":null,"longitude":null,"beds_count":"45","email_id":"jangidsunil1@gmail.com","website":"http://www.jivantahospitals.com/","ppn_available":false,"doctors_count":"4","rating":0,"avg_rating":0,"review_count":"NA","rating_count":"NA","reviews":"120","accreditions":"NA","treatment_cost":"NA","customer_expense":"NA","stay_duration":"NA","primary_phone":"0294-2466011","additional_phone":"7727866011","last_updated_at":"2022-02-26 00:00:00","ppn_benefits":{"ppn_spoc_phone_no":null,"nbhi_non_payable_waiver":null,"discount_on_opd_consultation":null,"discount_on_opd_investigation":null,"discount_on_health_check_up":null,"free_ambulance":null,"ppn_spoc_name":null},"poc":null,"ir":null},{"id":26368,"provider_id":"88223","name":"Singhal Memorial Hospital","address":"24 Siddarth Complex Hiran Magri, Sec-5 Near Sai Baba Temple","city":"Udaipur","state":"Rajasthan","postal_code":313002,"logo":"https://rules.nivabupa.com/media/default_hospital.svg","latitude":null,"longitude":null,"beds_count":"30","email_id":"singhalhospital.smh@gmail.com","website":"http://www.singhalhospitaludaipur.com/","ppn_available":false,"doctors_count":"2","rating":0,"avg_rating":0,"review_count":"NA","rating_count":"NA","reviews":"120","accreditions":"NA","treatment_cost":"NA","customer_expense":"NA","stay_duration":"NA","primary_phone":"0294-2465834","additional_phone":"8696789869","last_updated_at":"2022-03-29 00:00:00","ppn_benefits":{"ppn_spoc_phone_no":null,"nbhi_non_payable_waiver":null,"discount_on_opd_consultation":null,"discount_on_opd_investigation":null,"discount_on_health_check_up":null,"free_ambulance":null,"ppn_spoc_name":null},"poc":null,"ir":null},{"id":23611,"provider_id":"67210","name":"Madhuban Orthopaedic and Multispeciality Surgical Hospital Pvt. Ltd.","address":"71/28 Near Hiran Xray Above Anil Clinic Madhuban","city":"Udaipur","state":"Rajasthan","postal_code":313001,"logo":"https://rules.nivabupa.com/media/default_hospital.svg","latitude":24.59072,"longitude":73.69344,"beds_count":"30","email_id":"madhubanortho@gmail.com","website":null,"ppn_available":false,"doctors_count":"15","rating":0,"avg_rating":0,"review_count":"NA","rating_count":"NA","reviews":"120","accreditions":"NA","treatment_cost":"NA","customer_expense":"NA","stay_duration":"NA","primary_phone":"9752564542","additional_phone":"8870219372","last_updated_at":"2021-01-18 00:00:00","ppn_benefits":{"ppn_spoc_phone_no":null,"nbhi_non_payable_waiver":null,"discount_on_opd_consultation":null,"discount_on_opd_investigation":null,"discount_on_health_check_up":null,"free_ambulance":null,"ppn_spoc_name":null},"poc":null,"ir":null},{"id":26392,"provider_id":"88270","name":"Saraswati Narayan Hospital","address":"Near Darshan Dental College Loyra","city":"Udaipur","state":"Rajasthan","postal_code":313011,"logo":"https://rules.nivabupa.com/media/default_hospital.svg","latitude":null,"longitude":null,"beds_count":"25","email_id":"tpasnhospital@gmail.com","website":null,"ppn_available":false,"doctors_count":"9","rating":0,"avg_rating":0,"review_count":"NA","rating_count":"NA","reviews":"120","accreditions":"NA","treatment_cost":"NA","customer_expense":"NA","stay_duration":"NA","primary_phone":"9983551667","additional_phone":"9983551667","last_updated_at":"2022-03-29 00:00:00","ppn_benefits":{"ppn_spoc_phone_no":null,"nbhi_non_payable_waiver":null,"discount_on_opd_consultation":null,"discount_on_opd_investigation":null,"discount_on_health_check_up":null,"free_ambulance":null,"ppn_spoc_name":null},"poc":null,"ir":null},{"id":26393,"provider_id":"88271","name":"Bhandari Children Hospital and Research Center","address":"90-L Bhupalpura","city":"Udaipur","state":"Rajasthan","postal_code":313001,"logo":"https://rules.nivabupa.com/media/default_hospital.svg","latitude":null,"longitude":null,"beds_count":"75","email_id":"tpabch@gmail.com","website":"http://www.bhandarichildrenhospital.com/","ppn_available":false,"doctors_count":"4","rating":0,"avg_rating":0,"review_count":"NA","rating_count":"NA","reviews":"120","accreditions":"NABH Entry Level","treatment_cost":"NA","customer_expense":"NA","stay_duration":"NA","primary_phone":"0294-2414170","additional_phone":"8619179070","last_updated_at":"2022-03-29 00:00:00","ppn_benefits":{"ppn_spoc_phone_no":null,"nbhi_non_payable_waiver":null,"discount_on_opd_consultation":null,"discount_on_opd_investigation":null,"discount_on_health_check_up":null,"free_ambulance":null,"ppn_spoc_name":null},"poc":null,"ir":null},{"id":26728,"provider_id":"94072","name":"Shree Radhe Govind Hospital Pvt Ltd","address":"Plot No O & P Abhay Singh Ji Badi, Sardarpura","city":"Udaipur","state":"Rajasthan","postal_code":313001,"logo":"https://rules.nivabupa.com/media/default_hospital.svg","latitude":null,"longitude":null,"beds_count":"NA","email_id":"tpa.srghospitaludaipur@gmail.com","website":"http://www.srghospital.in/","ppn_available":false,"doctors_count":"NA","rating":0,"avg_rating":0,"review_count":"NA","rating_count":"NA","reviews":"120","accreditions":"NA","treatment_cost":"NA","customer_expense":"NA","stay_duration":"NA","primary_phone":"7229098486","additional_phone":null,"last_updated_at":"NA","ppn_benefits":{"ppn_spoc_phone_no":null,"nbhi_non_payable_waiver":null,"discount_on_opd_consultation":null,"discount_on_opd_investigation":null,"discount_on_health_check_up":null,"free_ambulance":null,"ppn_spoc_name":null},"poc":null,"ir":null},{"id":18365,"provider_id":"20720","name":"Rajasthan Hospital & Research Centre","address":"69 I-Block Sector-14 Hiran Magri","city":"Udaipur","state":"Rajasthan","postal_code":313001,"logo":"https://rules.nivabupa.com/media/default_hospital.svg","latitude":23.055186,"longitude":72.59641,"beds_count":"50","email_id":"karunagoyal@hotmail.com","website":null,"ppn_available":false,"doctors_count":"21","rating":0,"avg_rating":0,"review_count":"NA","rating_count":"NA","reviews":"120","accreditions":"NA","treatment_cost":"NA","customer_expense":"NA","stay_duration":"NA","primary_phone":"0294-2640852","additional_phone":"9414166785","last_updated_at":"2021-03-31 00:00:00","ppn_benefits":{"ppn_spoc_phone_no":null,"nbhi_non_payable_waiver":null,"discount_on_opd_consultation":null,"discount_on_opd_investigation":null,"discount_on_health_check_up":null,"free_ambulance":null,"ppn_spoc_name":null},"poc":null,"ir":null},{"id":18370,"provider_id":"20730","name":"J.B. Hospital","address":"22 Hiran Magri, Sector-6","city":"Udaipur","state":"Rajasthan","postal_code":313002,"logo":"https://rules.nivabupa.com/media/default_hospital.svg","latitude":24.559956,"longitude":73.718334,"beds_count":"25","email_id":"jbhudaipur@rediffmail.com","website":null,"ppn_available":false,"doctors_count":"9","rating":0,"avg_rating":0,"review_count":"NA","rating_count":"NA","reviews":"120","accreditions":"NA","treatment_cost":"NA","customer_expense":"NA","stay_duration":"NA","primary_phone":"0294-2462844","additional_phone":"0294-2462844","last_updated_at":"2021-03-31 00:00:00","ppn_benefits":{"ppn_spoc_phone_no":null,"nbhi_non_payable_waiver":null,"discount_on_opd_consultation":null,"discount_on_opd_investigation":null,"discount_on_health_check_up":null,"free_ambulance":null,"ppn_spoc_name":null},"poc":null,"ir":null},{"id":18372,"provider_id":"20737","name":"Dr. Babel's Medicare & Research Centre","address":"21 Fatehpura","city":"Udaipur","state":"Rajasthan","postal_code":313004,"logo":"https://rules.nivabupa.com/media/default_hospital.svg","latitude":24.614014,"longitude":73.686308,"beds_count":"35","email_id":"drdbabel@hotmail.com","website":null,"ppn_available":false,"doctors_count":"17","rating":0,"avg_rating":0,"review_count":"NA","rating_count":"NA","reviews":"120","accreditions":"NA","treatment_cost":"NA","customer_expense":"NA","stay_duration":"NA","primary_phone":"0294-2451621","additional_phone":"0294-2451621","last_updated_at":"2021-07-20 00:00:00","ppn_benefits":{"ppn_spoc_phone_no":null,"nbhi_non_payable_waiver":null,"discount_on_opd_consultation":null,"discount_on_opd_investigation":null,"discount_on_health_check_up":null,"free_ambulance":null,"ppn_spoc_name":null},"poc":null,"ir":null},{"id":18373,"provider_id":"20738","name":"Aravali Hospital","address":"332 Ambamata Scheme","city":"Udaipur","state":"Rajasthan","postal_code":313004,"logo":"https://rules.nivabupa.com/media/default_hospital.svg","latitude":24.585107,"longitude":73.670719,"beds_count":"30","email_id":"aravalihospital@yahoo.com","website":"http://www.aravalihospital.in/","ppn_available":false,"doctors_count":"13","rating":0,"avg_rating":0,"review_count":1,"rating_count":1,"reviews":"120","accreditions":"NABH Entry Level","treatment_cost":"NA","customer_expense":"NA","stay_duration":"7","primary_phone":"0294-2430222","additional_phone":"9352108108","last_updated_at":"2021-03-31 00:00:00","ppn_benefits":{"ppn_spoc_phone_no":null,"nbhi_non_payable_waiver":null,"discount_on_opd_consultation":null,"discount_on_opd_investigation":null,"discount_on_health_check_up":null,"free_ambulance":null,"ppn_spoc_name":null},"poc":null,"ir":null},{"id":18402,"provider_id":"20822","name":"Kalpana Nursing Home","address":"214-C Sardarpura","city":"Udaipur","state":"Rajasthan","postal_code":313001,"logo":"https://rules.nivabupa.com/media/default_hospital.svg","latitude":24.560863,"longitude":73.699973,"beds_count":"100","email_id":"knhpl@hotmail.com","website":null,"ppn_available":false,"doctors_count":"38","rating":0,"avg_rating":0,"review_count":"NA","rating_count":"NA","reviews":"120","accreditions":"JCI","treatment_cost":"NA","customer_expense":"NA","stay_duration":"7","primary_phone":"0294-2529244","additional_phone":"0294-2529244","last_updated_at":"2021-06-03 00:00:00","ppn_benefits":{"ppn_spoc_phone_no":null,"nbhi_non_payable_waiver":null,"discount_on_opd_consultation":null,"discount_on_opd_investigation":null,"discount_on_health_check_up":null,"free_ambulance":null,"ppn_spoc_name":null},"poc":null,"ir":null}]}