{"links":{"next":null,"previous":null},"count":17,"total_pages":1,"results":[{"id":18632,"provider_id":"21793","name":"Tiruvalla Medical Mission","address":"Post Box No-50","city":"Pathanamthitta","state":"Kerala","postal_code":689101,"logo":"https://rules.nivabupa.com/media/default_hospital.svg","latitude":9.373161,"longitude":76.563995,"beds_count":"300","email_id":"cashless@tmmhospital.org","website":"http://www.tmmhospital.org/","ppn_available":false,"doctors_count":"126","rating":4.59,"avg_rating":4.59,"review_count":17,"rating_count":17,"reviews":"120","accreditions":"NABH Entry Level","treatment_cost":"15,000-20,000","customer_expense":"NA","stay_duration":"8","primary_phone":"0469-2626097","additional_phone":"0469-2626097","last_updated_at":"2021-07-20 00:00:00","ppn_benefits":{"ppn_spoc_phone_no":null,"nbhi_non_payable_waiver":null,"discount_on_opd_consultation":null,"discount_on_opd_investigation":null,"discount_on_health_check_up":null,"free_ambulance":null,"ppn_spoc_name":null},"poc":null,"ir":null},{"id":21316,"provider_id":"48848","name":"Believers Church Medical College Hospital","address":"St.Thomas Nagar, Kuttapvzha P.O., Thiruvalla","city":"Pathanamthitta","state":"Kerala","postal_code":689103,"logo":"https://rules.nivabupa.com/media/default_hospital.svg","latitude":9.416748,"longitude":76.575061,"beds_count":"753","email_id":"sijiabraham@bcmch.org","website":"http://www.bcmch.org/","ppn_available":false,"doctors_count":"304","rating":4.46,"avg_rating":4.46,"review_count":28,"rating_count":28,"reviews":"120","accreditions":"NABH Higher Level","treatment_cost":"<5,000","customer_expense":"NA","stay_duration":"4","primary_phone":"0469-3023100","additional_phone":"0469-3023100","last_updated_at":"2021-04-21 00:00:00","ppn_benefits":{"ppn_spoc_phone_no":null,"nbhi_non_payable_waiver":null,"discount_on_opd_consultation":null,"discount_on_opd_investigation":null,"discount_on_health_check_up":null,"free_ambulance":null,"ppn_spoc_name":null},"poc":null,"ir":null},{"id":20531,"provider_id":"38545","name":"Muthoot Health Care Pvt. Ltd.","address":"College Road, Kozhencherry","city":"Pathanamthitta","state":"Kerala","postal_code":689641,"logo":"https://rules.nivabupa.com/media/default_hospital.svg","latitude":9.336066,"longitude":76.718044,"beds_count":"300","email_id":"mss.muthootmedicalcentre@gmail.com","website":"http://www.muthoothealthcare.com/","ppn_available":false,"doctors_count":"123","rating":4.41,"avg_rating":4.41,"review_count":17,"rating_count":17,"reviews":"120","accreditions":"NABH Higher Level","treatment_cost":"5,000-10,000","customer_expense":"NA","stay_duration":"4","primary_phone":"0468-231400","additional_phone":"7025173300","last_updated_at":"2021-07-20 00:00:00","ppn_benefits":{"ppn_spoc_phone_no":null,"nbhi_non_payable_waiver":null,"discount_on_opd_consultation":null,"discount_on_opd_investigation":null,"discount_on_health_check_up":null,"free_ambulance":null,"ppn_spoc_name":null},"poc":null,"ir":null},{"id":18690,"provider_id":"21973","name":"Pushpagiri Medical College Hospital","address":"Pathanamthitta Dist","city":"Pathanamthitta","state":"Kerala","postal_code":689101,"logo":"https://rules.nivabupa.com/media/default_hospital.svg","latitude":9.380959,"longitude":76.581693,"beds_count":"900","email_id":"cr@pushpagiri.in","website":"http://www.pushpagiri.in/","ppn_available":false,"doctors_count":"378","rating":4.35,"avg_rating":4.35,"review_count":17,"rating_count":17,"reviews":"120","accreditions":"NABH Entry Level","treatment_cost":"NA","customer_expense":"NA","stay_duration":"5","primary_phone":"0469-2700755","additional_phone":"9847910389","last_updated_at":"2020-11-27 00:00:00","ppn_benefits":{"ppn_spoc_phone_no":null,"nbhi_non_payable_waiver":null,"discount_on_opd_consultation":null,"discount_on_opd_investigation":null,"discount_on_health_check_up":null,"free_ambulance":null,"ppn_spoc_name":null},"poc":null,"ir":null},{"id":45411,"provider_id":"95912","name":"Precise Opsin Eye Hospital","address":"Packandathil Building, Near Union Bank, Pandalam","city":"Pathanamthitta","state":"Kerala","postal_code":689501,"logo":"https://rules.nivabupa.com/media/default_hospital.svg","latitude":null,"longitude":null,"beds_count":"NA","email_id":"preciseopsin@gmail.com","website":"http://www.preciseeye.in/","ppn_available":false,"doctors_count":"NA","rating":0,"avg_rating":1,"review_count":"NA","rating_count":"NA","reviews":"120","accreditions":"NA","treatment_cost":"NA","customer_expense":"NA","stay_duration":"NA","primary_phone":"0473-4298555","additional_phone":"8011885982","last_updated_at":"NA","ppn_benefits":{"ppn_spoc_phone_no":null,"nbhi_non_payable_waiver":null,"discount_on_opd_consultation":null,"discount_on_opd_investigation":null,"discount_on_health_check_up":null,"free_ambulance":null,"ppn_spoc_name":null},"poc":null,"ir":null},{"id":25672,"provider_id":"82422","name":"Chaithanya Eye Hospital and Research Institute - Pathanamthitta","address":"6-67/7-67/8 J Complex Manjadi P O","city":"Pathanamthitta","state":"Kerala","postal_code":689105,"logo":"https://rules.nivabupa.com/media/default_hospital.svg","latitude":0,"longitude":0,"beds_count":"10","email_id":"chaithanyatvla.acc@gmail.com","website":"https://www.chaithanya.org/","ppn_available":false,"doctors_count":"9","rating":0,"avg_rating":0,"review_count":1,"rating_count":1,"reviews":"120","accreditions":"NABH Entry Level","treatment_cost":"NA","customer_expense":"NA","stay_duration":"NA","primary_phone":"0469-2945500","additional_phone":"9562369529","last_updated_at":"2021-12-08 00:00:00","ppn_benefits":{"ppn_spoc_phone_no":null,"nbhi_non_payable_waiver":null,"discount_on_opd_consultation":null,"discount_on_opd_investigation":null,"discount_on_health_check_up":null,"free_ambulance":null,"ppn_spoc_name":null},"poc":null,"ir":null},{"id":22239,"provider_id":"61233","name":"Karunya Eye Hospital","address":"Raja Tower, Pandalam Po","city":"Pathanamthitta","state":"Kerala","postal_code":689501,"logo":"https://rules.nivabupa.com/media/default_hospital.svg","latitude":9.22735,"longitude":76.67772,"beds_count":"10","email_id":"tillygeorge183@gmail.com","website":null,"ppn_available":false,"doctors_count":"5","rating":0,"avg_rating":0,"review_count":"NA","rating_count":"NA","reviews":"120","accreditions":"NA","treatment_cost":"NA","customer_expense":"NA","stay_duration":"NA","primary_phone":"9745688854","additional_phone":"9745688854","last_updated_at":"2020-02-24 00:00:00","ppn_benefits":{"ppn_spoc_phone_no":null,"nbhi_non_payable_waiver":null,"discount_on_opd_consultation":null,"discount_on_opd_investigation":null,"discount_on_health_check_up":null,"free_ambulance":null,"ppn_spoc_name":null},"poc":null,"ir":null},{"id":25814,"provider_id":"83488","name":"St. Gregorios Medical Mission Hospital - Parumala","address":"Church Chengannur Parumala Mannar Road, Near Parumala Church, Thiruvalla","city":"Pathanamthitta","state":"Kerala","postal_code":689626,"logo":"https://rules.nivabupa.com/media/default_hospital.svg","latitude":0,"longitude":0,"beds_count":"238","email_id":"suneeshithithanam@gmail.com","website":"http://www.parumalahospital.com/","ppn_available":false,"doctors_count":"55","rating":0,"avg_rating":0,"review_count":8,"rating_count":8,"reviews":"120","accreditions":"NABH Higher Level","treatment_cost":"NA","customer_expense":"NA","stay_duration":"2","primary_phone":"0479-2317000","additional_phone":"9744541788","last_updated_at":"2021-12-29 00:00:00","ppn_benefits":{"ppn_spoc_phone_no":null,"nbhi_non_payable_waiver":null,"discount_on_opd_consultation":null,"discount_on_opd_investigation":null,"discount_on_health_check_up":null,"free_ambulance":null,"ppn_spoc_name":null},"poc":null,"ir":null},{"id":26667,"provider_id":"93544","name":"Holy Cross Hospital","address":"Xxvii/37 38, Holy Cross Junction, Karuvatta Near Fire Station, Adoor","city":"Pathanamthitta","state":"Kerala","postal_code":691523,"logo":"https://rules.nivabupa.com/media/default_hospital.svg","latitude":null,"longitude":null,"beds_count":"NA","email_id":"holycrosshospitaladoor@gmail.com","website":"http://www. holycrosshospitaladoor.com/","ppn_available":false,"doctors_count":"NA","rating":0,"avg_rating":0,"review_count":"NA","rating_count":"NA","reviews":"120","accreditions":"NA","treatment_cost":"NA","customer_expense":"NA","stay_duration":"NA","primary_phone":"4734234502","additional_phone":"9496550205","last_updated_at":"NA","ppn_benefits":{"ppn_spoc_phone_no":null,"nbhi_non_payable_waiver":null,"discount_on_opd_consultation":null,"discount_on_opd_investigation":null,"discount_on_health_check_up":null,"free_ambulance":null,"ppn_spoc_name":null},"poc":null,"ir":null},{"id":18519,"provider_id":"21366","name":"Christian Mission Hospital","address":"M.C. Road Pandalam","city":"Pathanamthitta","state":"Kerala","postal_code":689501,"logo":"https://rules.nivabupa.com/media/default_hospital.svg","latitude":9.265928,"longitude":76.788054,"beds_count":"100","email_id":"cmhospitalp@yahoo.com","website":null,"ppn_available":false,"doctors_count":"30","rating":0,"avg_rating":0,"review_count":2,"rating_count":2,"reviews":"120","accreditions":"NABH Entry Level","treatment_cost":"NA","customer_expense":"NA","stay_duration":"4","primary_phone":"04734-252246","additional_phone":"9495682611","last_updated_at":"2021-06-03 00:00:00","ppn_benefits":{"ppn_spoc_phone_no":null,"nbhi_non_payable_waiver":null,"discount_on_opd_consultation":null,"discount_on_opd_investigation":null,"discount_on_health_check_up":null,"free_ambulance":null,"ppn_spoc_name":null},"poc":null,"ir":null},{"id":22234,"provider_id":"61156","name":"Karunya Eye Hospital","address":"City Plaza, Adoor P.O.","city":"Pathanamthitta","state":"Kerala","postal_code":691523,"logo":"https://rules.nivabupa.com/media/default_hospital.svg","latitude":9.1545,"longitude":76.73249,"beds_count":"10","email_id":"tillygeorge183@gmail.com","website":null,"ppn_available":false,"doctors_count":"5","rating":0,"avg_rating":0,"review_count":"NA","rating_count":"NA","reviews":"120","accreditions":"NABH Entry Level","treatment_cost":"NA","customer_expense":"NA","stay_duration":"NA","primary_phone":"9745688854","additional_phone":"8304930890","last_updated_at":"2021-03-12 00:00:00","ppn_benefits":{"ppn_spoc_phone_no":null,"nbhi_non_payable_waiver":null,"discount_on_opd_consultation":null,"discount_on_opd_investigation":null,"discount_on_health_check_up":null,"free_ambulance":null,"ppn_spoc_name":null},"poc":null,"ir":null},{"id":44701,"provider_id":"94226","name":"Chitra Multi Speciality Hospital","address":"M.C. Road, Pandalam","city":"Pathanamthitta","state":"Kerala","postal_code":689501,"logo":"https://rules.nivabupa.com/media/default_hospital.svg","latitude":null,"longitude":null,"beds_count":"NA","email_id":"chitrahospital@rediffmail.com","website":null,"ppn_available":false,"doctors_count":"NA","rating":0,"avg_rating":0,"review_count":2,"rating_count":2,"reviews":"120","accreditions":"NA","treatment_cost":"NA","customer_expense":"NA","stay_duration":"NA","primary_phone":"0473-4255546","additional_phone":"9497378592","last_updated_at":"NA","ppn_benefits":{"ppn_spoc_phone_no":null,"nbhi_non_payable_waiver":null,"discount_on_opd_consultation":null,"discount_on_opd_investigation":null,"discount_on_health_check_up":null,"free_ambulance":null,"ppn_spoc_name":null},"poc":null,"ir":null},{"id":23343,"provider_id":"66317","name":"Ahalia Foundation Eye Hospital-PATHANAMTHITTA 1","address":"Thekkemuriyil Arcade College Road Pathanamthitta","city":"Pathanamthitta","state":"Kerala","postal_code":689645,"logo":"https://rules.nivabupa.com/media/default_hospital.svg","latitude":9.26297,"longitude":76.78353,"beds_count":"3","email_id":"corpservice@afeh.org","website":null,"ppn_available":false,"doctors_count":"3","rating":0,"avg_rating":0,"review_count":"NA","rating_count":"NA","reviews":"120","accreditions":"NA","treatment_cost":"NA","customer_expense":"NA","stay_duration":"NA","primary_phone":"9400247623","additional_phone":"9400247623","last_updated_at":"2021-03-31 00:00:00","ppn_benefits":{"ppn_spoc_phone_no":null,"nbhi_non_payable_waiver":null,"discount_on_opd_consultation":null,"discount_on_opd_investigation":null,"discount_on_health_check_up":null,"free_ambulance":null,"ppn_spoc_name":null},"poc":null,"ir":null},{"id":19242,"provider_id":"28708","name":"Vasan Eye Care Hospital Tiruvalla","address":"No 640/1 Ward No.7 Mc Road Tiruvalla (Near Indusand Bank)","city":"Pathanamthitta","state":"Kerala","postal_code":689101,"logo":"https://rules.nivabupa.com/media/default_hospital.svg","latitude":9.38452,"longitude":76.57714,"beds_count":"10","email_id":"thiruvallatpa2012@gmail.com","website":null,"ppn_available":false,"doctors_count":"5","rating":0,"avg_rating":0,"review_count":"NA","rating_count":"NA","reviews":"120","accreditions":"NA","treatment_cost":"NA","customer_expense":"NA","stay_duration":"NA","primary_phone":"0469-3989000","additional_phone":"9539008012","last_updated_at":"2021-07-20 00:00:00","ppn_benefits":{"ppn_spoc_phone_no":null,"nbhi_non_payable_waiver":null,"discount_on_opd_consultation":null,"discount_on_opd_investigation":null,"discount_on_health_check_up":null,"free_ambulance":null,"ppn_spoc_name":null},"poc":null,"ir":null},{"id":20557,"provider_id":"39091","name":"MGM Muthoot Medical Center Pvt Ltd.","address":"Ring Road","city":"Pathanamthitta","state":"Kerala","postal_code":689645,"logo":"https://rules.nivabupa.com/media/default_hospital.svg","latitude":9.337905,"longitude":76.710744,"beds_count":"300","email_id":"muthootmc@sify.com","website":"http://www.muthoothealthcare.com/","ppn_available":false,"doctors_count":"123","rating":0,"avg_rating":0,"review_count":4,"rating_count":4,"reviews":"120","accreditions":"NABH Entry Level","treatment_cost":"NA","customer_expense":"NA","stay_duration":"NA","primary_phone":"0468-3005500","additional_phone":"9961405612","last_updated_at":"2021-03-31 00:00:00","ppn_benefits":{"ppn_spoc_phone_no":null,"nbhi_non_payable_waiver":null,"discount_on_opd_consultation":null,"discount_on_opd_investigation":null,"discount_on_health_check_up":null,"free_ambulance":null,"ppn_spoc_name":null},"poc":null,"ir":null},{"id":21616,"provider_id":"52676","name":"Life Line Super Speciality Hospital","address":"14Th Mile, Melood(P.O), Adoor","city":"Pathanamthitta","state":"Kerala","postal_code":691523,"logo":"https://rules.nivabupa.com/media/default_hospital.svg","latitude":9.16348,"longitude":76.70631,"beds_count":"150","email_id":"info@lifelinehospitalkerala.com","website":null,"ppn_available":false,"doctors_count":"62","rating":0,"avg_rating":0,"review_count":8,"rating_count":8,"reviews":"120","accreditions":"NABH Entry Level","treatment_cost":"NA","customer_expense":"NA","stay_duration":"4","primary_phone":"0473-4223377","additional_phone":"9847529125","last_updated_at":"2021-03-31 00:00:00","ppn_benefits":{"ppn_spoc_phone_no":null,"nbhi_non_payable_waiver":null,"discount_on_opd_consultation":null,"discount_on_opd_investigation":null,"discount_on_health_check_up":null,"free_ambulance":null,"ppn_spoc_name":null},"poc":null,"ir":null},{"id":47300,"provider_id":"102464","name":"St.Thomas Hospital","address":"P.O. Malakkara","city":"Pathanamthitta","state":"Kerala","postal_code":689532,"logo":"https://rules.nivabupa.com/media/default_hospital.svg","latitude":null,"longitude":null,"beds_count":"NA","email_id":"stthomashospitalmalakkara@gmail.com","website":"https://www.stthomashospitalmalakkara.com/","ppn_available":false,"doctors_count":"NA","rating":0,"avg_rating":1,"review_count":"NA","rating_count":"NA","reviews":"120","accreditions":"NA","treatment_cost":"NA","customer_expense":"NA","stay_duration":"NA","primary_phone":"9447265350","additional_phone":"9447265350","last_updated_at":"NA","ppn_benefits":{"ppn_spoc_phone_no":null,"nbhi_non_payable_waiver":null,"discount_on_opd_consultation":null,"discount_on_opd_investigation":null,"discount_on_health_check_up":null,"free_ambulance":null,"ppn_spoc_name":null},"poc":null,"ir":null}]}