{"links":{"next":null,"previous":null},"count":6,"total_pages":1,"results":[{"id":24184,"provider_id":"70205","name":"Dhillon Eye Hospital and Laser Centre","address":"Opp Amm Khas Bhag, Bassi Road Sirhind","city":"Fatehgarh Sahib","state":"Punjab","postal_code":140406,"logo":"https://rules.nivabupa.com/media/default_hospital.svg","latitude":30.6361,"longitude":76.39259,"beds_count":"1","email_id":"dhilloneye@gmail.com","website":null,"ppn_available":false,"doctors_count":"2","rating":0,"avg_rating":0,"review_count":"NA","rating_count":"NA","reviews":"120","accreditions":"NA","treatment_cost":"NA","customer_expense":"NA","stay_duration":"NA","primary_phone":"8198800350","additional_phone":"8198800350","last_updated_at":"2021-03-15 00:00:00","ppn_benefits":{"ppn_spoc_phone_no":null,"nbhi_non_payable_waiver":null,"discount_on_opd_consultation":null,"discount_on_opd_investigation":null,"discount_on_health_check_up":null,"free_ambulance":null,"ppn_spoc_name":null},"poc":null,"ir":null},{"id":23199,"provider_id":"65572","name":"Kaushal Nursing Home","address":"Near Krishan Mandir, Gole Market, Mandi Gobindgarh, Fatehgarh Sahib","city":"Fatehgarh Sahib","state":"Punjab","postal_code":147301,"logo":"https://rules.nivabupa.com/media/default_hospital.svg","latitude":30.66753,"longitude":76.29241,"beds_count":"15","email_id":"corporate.kaushalnursinghome@gmail.com","website":null,"ppn_available":false,"doctors_count":"2","rating":0,"avg_rating":0,"review_count":1,"rating_count":1,"reviews":"120","accreditions":"NA","treatment_cost":"NA","customer_expense":"NA","stay_duration":"NA","primary_phone":"9815504476","additional_phone":"9815504476","last_updated_at":"2021-04-21 00:00:00","ppn_benefits":{"ppn_spoc_phone_no":null,"nbhi_non_payable_waiver":null,"discount_on_opd_consultation":null,"discount_on_opd_investigation":null,"discount_on_health_check_up":null,"free_ambulance":null,"ppn_spoc_name":null},"poc":null,"ir":null},{"id":23695,"provider_id":"67572","name":"Sohal Hospital Multispeciality Centre","address":"Bhatti Road, Near Railway Flyover, Sirhind","city":"Fatehgarh Sahib","state":"Punjab","postal_code":140406,"logo":"https://rules.nivabupa.com/media/default_hospital.svg","latitude":30.61558,"longitude":76.38959,"beds_count":"26","email_id":"drkssohal@gmail.com","website":null,"ppn_available":false,"doctors_count":"11","rating":0,"avg_rating":0,"review_count":"NA","rating_count":"NA","reviews":"120","accreditions":"NA","treatment_cost":"NA","customer_expense":"NA","stay_duration":"NA","primary_phone":"9815021425","additional_phone":"9815328186","last_updated_at":"2020-12-31 00:00:00","ppn_benefits":{"ppn_spoc_phone_no":null,"nbhi_non_payable_waiver":null,"discount_on_opd_consultation":null,"discount_on_opd_investigation":null,"discount_on_health_check_up":null,"free_ambulance":null,"ppn_spoc_name":null},"poc":null,"ir":null},{"id":24081,"provider_id":"69580","name":"Rana Nursing Home Fatehgarh Sahib","address":"Near Bdo Office Sirhind","city":"Fatehgarh Sahib","state":"Punjab","postal_code":140406,"logo":"https://rules.nivabupa.com/media/default_hospital.svg","latitude":30.61597,"longitude":76.38109,"beds_count":"25","email_id":"ranapiles001@yahoo.in","website":"http://www.ranapileshospital.com/","ppn_available":false,"doctors_count":"9","rating":0,"avg_rating":0,"review_count":1,"rating_count":1,"reviews":"120","accreditions":"NA","treatment_cost":"NA","customer_expense":"NA","stay_duration":"NA","primary_phone":"9592379100","additional_phone":"9592800267","last_updated_at":"2021-03-18 00:00:00","ppn_benefits":{"ppn_spoc_phone_no":null,"nbhi_non_payable_waiver":null,"discount_on_opd_consultation":null,"discount_on_opd_investigation":null,"discount_on_health_check_up":null,"free_ambulance":null,"ppn_spoc_name":null},"poc":null,"ir":null},{"id":21497,"provider_id":"50897","name":"Indus Fatehgarh Sahib Hospital","address":"Landran Fatehgarh Highway, Pirjain","city":"Fatehgarh Sahib","state":"Punjab","postal_code":140406,"logo":"https://rules.nivabupa.com/media/default_hospital.svg","latitude":30.64291,"longitude":76.47583,"beds_count":"66","email_id":"tejpreet@indushospital.in","website":"http://www.indushealthcare.in/","ppn_available":false,"doctors_count":"28","rating":0,"avg_rating":0,"review_count":1,"rating_count":1,"reviews":"120","accreditions":"NABH Higher Level","treatment_cost":"NA","customer_expense":"NA","stay_duration":"0","primary_phone":"9888909584","additional_phone":"01762-238382","last_updated_at":"2021-03-31 00:00:00","ppn_benefits":{"ppn_spoc_phone_no":null,"nbhi_non_payable_waiver":null,"discount_on_opd_consultation":null,"discount_on_opd_investigation":null,"discount_on_health_check_up":null,"free_ambulance":null,"ppn_spoc_name":null},"poc":null,"ir":null},{"id":21603,"provider_id":"51336","name":"Life Care Hospital...","address":"Opp Bus Stand, Behind Gurudwara, Khamano","city":"Fatehgarh Sahib","state":"Punjab","postal_code":141801,"logo":"https://rules.nivabupa.com/media/default_hospital.svg","latitude":30.81414,"longitude":76.34638,"beds_count":"25","email_id":"lifecarehospitalkhamano@gmail.com","website":null,"ppn_available":false,"doctors_count":"11","rating":0,"avg_rating":0,"review_count":"NA","rating_count":"NA","reviews":"120","accreditions":"NA","treatment_cost":"NA","customer_expense":"NA","stay_duration":"4","primary_phone":"9855210002","additional_phone":"9417915321","last_updated_at":"2021-01-15 00:00:00","ppn_benefits":{"ppn_spoc_phone_no":null,"nbhi_non_payable_waiver":null,"discount_on_opd_consultation":null,"discount_on_opd_investigation":null,"discount_on_health_check_up":null,"free_ambulance":null,"ppn_spoc_name":null},"poc":null,"ir":null}]}