{"links":{"next":null,"previous":null},"count":3,"total_pages":1,"results":[{"id":22892,"provider_id":"64200","name":"Iswarya Fertility Services Pvt. Ltd. Ramanathapuram","address":"No:49/1 Moolakothalam Street, Madurai Main Road Ramnad, Ramanathapuram, Tamilnadu","city":"Ramanathapuram","state":"Tamil Nadu","postal_code":623501,"logo":"https://rules.nivabupa.com/media/default_hospital.svg","latitude":9.36555,"longitude":78.8206,"beds_count":"16","email_id":"iswarya.in@gmail.com","website":null,"ppn_available":false,"doctors_count":"3","rating":0,"avg_rating":0,"review_count":"NA","rating_count":"NA","reviews":"120","accreditions":"NABH Entry Level","treatment_cost":"NA","customer_expense":"NA","stay_duration":"NA","primary_phone":"9976610022","additional_phone":"9976610022","last_updated_at":"2021-01-13 00:00:00","ppn_benefits":{"ppn_spoc_phone_no":null,"nbhi_non_payable_waiver":null,"discount_on_opd_consultation":null,"discount_on_opd_investigation":null,"discount_on_health_check_up":null,"free_ambulance":null,"ppn_spoc_name":null},"poc":null,"ir":null},{"id":19672,"provider_id":"31566","name":"Vasan Eye Care Hospital Paramakudi","address":"No. 2/262 - D Railway Feeder Road Paramakudi Ramnad District","city":"Ramanathapuram","state":"Tamil Nadu","postal_code":623707,"logo":"https://rules.nivabupa.com/media/default_hospital.svg","latitude":9.54011,"longitude":78.69149,"beds_count":"10","email_id":"recovery.tpa@vasaneye.in","website":"http://vasaneye.com/","ppn_available":false,"doctors_count":"5","rating":0,"avg_rating":0,"review_count":"NA","rating_count":"NA","reviews":"120","accreditions":"NA","treatment_cost":"NA","customer_expense":"NA","stay_duration":"NA","primary_phone":"04564-398900","additional_phone":"9585548967","last_updated_at":"2021-07-20 00:00:00","ppn_benefits":{"ppn_spoc_phone_no":null,"nbhi_non_payable_waiver":null,"discount_on_opd_consultation":null,"discount_on_opd_investigation":null,"discount_on_health_check_up":null,"free_ambulance":null,"ppn_spoc_name":null},"poc":null,"ir":null},{"id":18760,"provider_id":"22274","name":"Vasan Eye Care Hospital Ramnad","address":"78/143 Salai St Aringnar Anna Salai Ramanathpuram","city":"Ramanathapuram","state":"Tamil Nadu","postal_code":623501,"logo":"https://rules.nivabupa.com/media/default_hospital.svg","latitude":9.36739,"longitude":78.82965,"beds_count":"65","email_id":"recovery.tpa@vasaneye.in","website":"http://vasaneye.com/","ppn_available":false,"doctors_count":"35","rating":0,"avg_rating":0,"review_count":"NA","rating_count":"NA","reviews":"120","accreditions":"NA","treatment_cost":"NA","customer_expense":"NA","stay_duration":"NA","primary_phone":"04567-398900","additional_phone":"9585548967","last_updated_at":"2021-03-31 00:00:00","ppn_benefits":{"ppn_spoc_phone_no":null,"nbhi_non_payable_waiver":null,"discount_on_opd_consultation":null,"discount_on_opd_investigation":null,"discount_on_health_check_up":null,"free_ambulance":null,"ppn_spoc_name":null},"poc":null,"ir":null}]}