{"links":{"next":null,"previous":null},"count":7,"total_pages":1,"results":[{"id":46374,"provider_id":"100289","name":"Mahalaksmi Hospital","address":"6A, Jubilee Road (Near Bus Stand) Ulundurpet, Kallakurchi Dt","city":"Villupuram","state":"Tamil Nadu","postal_code":606107,"logo":"https://rules.nivabupa.com/media/default_hospital.svg","latitude":null,"longitude":null,"beds_count":"NA","email_id":"mahahospinsurnace@gmail.com","website":null,"ppn_available":false,"doctors_count":"NA","rating":0,"avg_rating":1,"review_count":"NA","rating_count":"NA","reviews":"120","accreditions":"NA","treatment_cost":"NA","customer_expense":"NA","stay_duration":"NA","primary_phone":"04149-220335","additional_phone":"9840866690","last_updated_at":"NA","ppn_benefits":{"ppn_spoc_phone_no":null,"nbhi_non_payable_waiver":null,"discount_on_opd_consultation":null,"discount_on_opd_investigation":null,"discount_on_health_check_up":null,"free_ambulance":null,"ppn_spoc_name":null},"poc":null,"ir":null},{"id":21878,"provider_id":"58614","name":"Durai Gastrocare Hospital","address":"Kamal Nagar Extension, Op.Collector Office","city":"Villupuram","state":"Tamil Nadu","postal_code":605602,"logo":"https://rules.nivabupa.com/media/default_hospital.svg","latitude":11.93347,"longitude":79.48477,"beds_count":"35","email_id":"duraigastrocare@gmail.com","website":null,"ppn_available":false,"doctors_count":"3","rating":0,"avg_rating":0,"review_count":"NA","rating_count":"NA","reviews":"120","accreditions":"NA","treatment_cost":"NA","customer_expense":"NA","stay_duration":"NA","primary_phone":"04161-251351","additional_phone":"04161-251351","last_updated_at":"2021-03-31 00:00:00","ppn_benefits":{"ppn_spoc_phone_no":null,"nbhi_non_payable_waiver":null,"discount_on_opd_consultation":null,"discount_on_opd_investigation":null,"discount_on_health_check_up":null,"free_ambulance":null,"ppn_spoc_name":null},"poc":null,"ir":null},{"id":23981,"provider_id":"69191","name":"Sumathy Hospital","address":"No. 39 Mampazhapattu Road","city":"Villupuram","state":"Tamil Nadu","postal_code":605602,"logo":"https://rules.nivabupa.com/media/default_hospital.svg","latitude":11.93864,"longitude":79.47914,"beds_count":"81","email_id":"raja22974@yahoo.com","website":null,"ppn_available":false,"doctors_count":"34","rating":0,"avg_rating":0,"review_count":"NA","rating_count":"NA","reviews":"120","accreditions":"NA","treatment_cost":"NA","customer_expense":"NA","stay_duration":"8","primary_phone":"9443362772","additional_phone":"8925072072","last_updated_at":"2021-02-16 00:00:00","ppn_benefits":{"ppn_spoc_phone_no":null,"nbhi_non_payable_waiver":null,"discount_on_opd_consultation":null,"discount_on_opd_investigation":null,"discount_on_health_check_up":null,"free_ambulance":null,"ppn_spoc_name":null},"poc":null,"ir":null},{"id":21705,"provider_id":"57091","name":"I Med Super Speciality Hospitals","address":"55/ 1B Opposit To Fire Station, Tindivanam","city":"Villupuram","state":"Tamil Nadu","postal_code":604001,"logo":"https://rules.nivabupa.com/media/default_hospital.svg","latitude":12.21907,"longitude":79.6575,"beds_count":"104","email_id":"imedinsurance19@gmail.com","website":"http://www.imedhospitals.com/","ppn_available":false,"doctors_count":"16","rating":0,"avg_rating":0,"review_count":"NA","rating_count":"NA","reviews":"120","accreditions":"NA","treatment_cost":"NA","customer_expense":"NA","stay_duration":"NA","primary_phone":"9600456315","additional_phone":"9600456315","last_updated_at":"2021-03-31 00:00:00","ppn_benefits":{"ppn_spoc_phone_no":null,"nbhi_non_payable_waiver":null,"discount_on_opd_consultation":null,"discount_on_opd_investigation":null,"discount_on_health_check_up":null,"free_ambulance":null,"ppn_spoc_name":null},"poc":null,"ir":null},{"id":21649,"provider_id":"55621","name":"E.S Hospital","address":"32 B Trichy Trunk Road, Villupuram","city":"Villupuram","state":"Tamil Nadu","postal_code":605602,"logo":"https://rules.nivabupa.com/media/default_hospital.svg","latitude":11.93647,"longitude":79.485,"beds_count":"17","email_id":"eshinsurance@gmail.com","website":null,"ppn_available":false,"doctors_count":"6","rating":0,"avg_rating":0,"review_count":"NA","rating_count":"NA","reviews":"120","accreditions":"NABH Entry Level","treatment_cost":"NA","customer_expense":"NA","stay_duration":"0","primary_phone":"04146-251036","additional_phone":"04146-251036","last_updated_at":"2021-03-31 00:00:00","ppn_benefits":{"ppn_spoc_phone_no":null,"nbhi_non_payable_waiver":null,"discount_on_opd_consultation":null,"discount_on_opd_investigation":null,"discount_on_health_check_up":null,"free_ambulance":null,"ppn_spoc_name":null},"poc":null,"ir":null},{"id":19665,"provider_id":"31553","name":"Vasan Eye Care Hospital Villupuram","address":"No.13 Hospital Road Opp. State Bank Villupuram","city":"Villupuram","state":"Tamil Nadu","postal_code":605602,"logo":"https://rules.nivabupa.com/media/default_hospital.svg","latitude":11.94553,"longitude":73.48878,"beds_count":"10","email_id":"recovery.tpa@vasaneye.in","website":"http://vasaneye.com/","ppn_available":false,"doctors_count":"5","rating":0,"avg_rating":0,"review_count":"NA","rating_count":"NA","reviews":"120","accreditions":"NA","treatment_cost":"NA","customer_expense":"NA","stay_duration":"NA","primary_phone":"04146-398900","additional_phone":"04146-398900","last_updated_at":"2021-07-20 00:00:00","ppn_benefits":{"ppn_spoc_phone_no":null,"nbhi_non_payable_waiver":null,"discount_on_opd_consultation":null,"discount_on_opd_investigation":null,"discount_on_health_check_up":null,"free_ambulance":null,"ppn_spoc_name":null},"poc":null,"ir":null},{"id":17985,"provider_id":"20079","name":"Dr. Agarwal's Eye Hospital Villupuram","address":"19 Trichy Trunk Road","city":"Villupuram","state":"Tamil Nadu","postal_code":605602,"logo":"https://rules.nivabupa.com/media/hospital_images/20079.png","latitude":11.97094,"longitude":79.503715,"beds_count":"10","email_id":"tpa@dragarwal.com","website":"https://www.dragarwal.com/","ppn_available":false,"doctors_count":"5","rating":0,"avg_rating":0,"review_count":"NA","rating_count":"NA","reviews":"120","accreditions":"NA","treatment_cost":"NA","customer_expense":"NA","stay_duration":"NA","primary_phone":"04146-227556","additional_phone":"9444448619","last_updated_at":"2021-07-20 00:00:00","ppn_benefits":{"ppn_spoc_phone_no":null,"nbhi_non_payable_waiver":null,"discount_on_opd_consultation":null,"discount_on_opd_investigation":null,"discount_on_health_check_up":null,"free_ambulance":null,"ppn_spoc_name":null},"poc":null,"ir":null}]}